py4tfidf/__init__.py
py4tfidf/vectorizer.py
py4tfidf-0.0.4.dist-info/METADATA
py4tfidf-0.0.4.dist-info/WHEEL
py4tfidf-0.0.4.dist-info/top_level.txt
py4tfidf-0.0.4.dist-info/RECORD
