Metadata-Version: 2.1
Name: py4tfidf
Version: 0.0.4
Summary: Term Frequency – Inverse Document Frequency (TF-IDF) Python Library
Home-page: https://github.com/luthfi118/py4tfidf
Author: Mgs. M. Luthfi Ramadhan
Author-email: luthfir96@gmail.com
License: UNKNOWN
Platform: UNKNOWN
Classifier: Programming Language :: Python :: 3
Classifier: License :: OSI Approved :: MIT License
Classifier: Operating System :: OS Independent
Requires-Python: >=3.7
